{
    "title": "Moons Extraxtions[Co-op Horror]",
    "id": 3416646,
    "price": "$2.80",
    "cover_image": "https://img.itch.zone/aW1nLzIwMzg5ODI3LmpwZw==/315x250%23c/IEz8mU.jpg",
    "links": {
        "comments": "https://smart-studiulation.itch.io/moons-extraxtionsco-op-horror/comments",
        "self": "https://smart-studiulation.itch.io/moons-extraxtionsco-op-horror"
    },
    "tags": [
        "adventure",
        "atmospheric",
        "first-person",
        "horror",
        "multiplayer",
        "no-ai",
        "pixel-art",
        "platformer",
        "psychological-horror",
        "puzzle",
        "short"
    ],
    "authors": [
        {
            "name": "Smart-Studiulation",
            "url": "https://smart-studiulation.itch.io"
        }
    ]
}