{
    "guid": "https://untiedgames.itch.io/super-pixel-projectiles-pack-1",
    "title": "Super Pixel Projectiles Pack 1 [50% Off] [$4.99]",
    "plainTitle": "Super Pixel Projectiles Pack 1",
    "imageurl": "https://img.itch.zone/aW1nLzEwNTA3ODEyLmdpZg==/315x250%23c/AC1Vw3.gif",
    "price": "$4.99",
    "currency": "USD",
    "discountpercent": "50",
    "fullPrice": "$9.99",
    "saleends": "Mon, 25 Aug 2025 17:00:00 GMT",
    "link": "https://untiedgames.itch.io/super-pixel-projectiles-pack-1",
    "description": "High quality animated projectiles for your game!\n<img alt=\"Super Pixel Projectiles Pack 1\" src=\"https://img.itch.zone/aW1nLzEwNTA3ODEyLmdpZg==/315x250%23c/AC1Vw3.gif\"/>",
    "pubDate": "Sat, 12 Nov 2022 01:43:45 GMT",
    "createDate": "Sat, 12 Nov 2022 01:43:45 GMT",
    "updateDate": "Thu, 16 Nov 2023 16:30:42 GMT",
    "platforms": null
}