{
    "authors": [
        {
            "name": "car mahdi",
            "url": "https://car-mahdi.itch.io"
        }
    ],
    "id": 3742375,
    "price": "$0.00",
    "tags": [
        "2d",
        "godo",
        "no-ai"
    ],
    "cover_image": "https://img.itch.zone/aW1nLzIyMjc2MTM1LnBuZw==/315x250%23c/QvSAR3.png",
    "links": {
        "self": "https://car-mahdi.itch.io/car-game-2d",
        "comments": "https://car-mahdi.itch.io/car-game-2d/comments"
    },
    "title": "car game 2D"
}