{
    "price": "$0.00",
    "links": {
        "self": "https://u-b-u.itch.io/connect-the-dots"
    },
    "authors": [
        {
            "name": "\u200e \u200e \u200e \u200e \u200e \u200e \u200e \u200e",
            "url": "https://u-b-u.itch.io"
        }
    ],
    "cover_image": "https://img.itch.zone/aW1nLzIyMDk2NDc3LnBuZw==/315x250%23c/hVF1MM.png",
    "id": 3708391,
    "title": "Connect the Dots",
    "tags": [
        "experimental",
        "female-protagonist",
        "kinetic-novel",
        "lesbian",
        "mystery",
        "narrative",
        "no-ai",
        "short",
        "story-rich",
        "text-based",
        "visual-novel",
        "yuri"
    ]
}