{
    "guid": "https://free-game-assets.itch.io/7-explosion-sprites",
    "title": "7 Explosion Sprites [90% Off] [$0.60]",
    "plainTitle": "7 Explosion Sprites",
    "imageurl": "https://img.itch.zone/aW1hZ2UvMTUzOTMwLzcwNTMzMi5qcGc=/315x250%23c/KA6SV8.jpg",
    "price": "$0.60",
    "currency": "USD",
    "discountpercent": "90",
    "fullPrice": "$6.00",
    "saleends": "Fri, 01 Aug 2025 12:00:00 GMT",
    "link": "https://free-game-assets.itch.io/7-explosion-sprites",
    "description": "7 Explosion Sprites for video games\n<img alt=\"7 Explosion Sprites\" src=\"https://img.itch.zone/aW1hZ2UvMTUzOTMwLzcwNTMzMi5qcGc=/315x250%23c/KA6SV8.jpg\"/>",
    "pubDate": "Sun, 25 Jun 2017 14:12:17 GMT",
    "createDate": "Sun, 25 Jun 2017 14:12:17 GMT",
    "updateDate": "Fri, 15 Jan 2021 18:34:27 GMT",
    "platforms": null
}