{
    "guid": "https://nyknck.itch.io/bloodfx",
    "title": "Pixel Art Blood Effect - FX020 [Free]",
    "plainTitle": "Pixel Art Blood Effect - FX020",
    "imageurl": "https://img.itch.zone/aW1nLzI5MDE0ODAuZ2lm/315x250%23c/IFey%2Bp.gif",
    "price": "$0.00",
    "currency": "USD",
    "link": "https://nyknck.itch.io/bloodfx",
    "description": "<img alt=\"Pixel Art Blood Effect - FX020\" src=\"https://img.itch.zone/aW1nLzI5MDE0ODAuZ2lm/315x250%23c/IFey%2Bp.gif\"/>",
    "pubDate": "Wed, 22 Jan 2020 13:13:41 GMT",
    "createDate": "Wed, 22 Jan 2020 13:13:41 GMT",
    "updateDate": "Fri, 24 Jan 2020 14:58:09 GMT",
    "platforms": null
}