{
    "authors": [
        {
            "name": "BALD",
            "url": "https://bald7.itch.io"
        }
    ],
    "id": 3753393,
    "tags": [],
    "cover_image": "https://img.itch.zone/aW1nLzIyMzQwMzAwLmpwZw==/315x250%23c/qf9Cmj.jpg",
    "links": {
        "devlog": "https://bald7.itch.io/spongbob-basics-retextured-android/devlog",
        "self": "https://bald7.itch.io/spongbob-basics-retextured-android",
        "comments": "https://bald7.itch.io/spongbob-basics-retextured-android/comments"
    },
    "title": "Spongbob Basics retextured Android"
}