{
    "guid": "https://xyezawr.itch.io/free-pixel-effects-pack-14-mini-magick-shoots-4",
    "title": "Free Pixel Effects Pack #14 - Mini Magick Shoots 4 [Free]",
    "plainTitle": "Free Pixel Effects Pack #14 - Mini Magick Shoots 4",
    "imageurl": "https://img.itch.zone/aW1nLzQzNzUxNzguZ2lm/315x250%23c/oVSWCm.gif",
    "price": "$0.00",
    "currency": "USD",
    "link": "https://xyezawr.itch.io/free-pixel-effects-pack-14-mini-magick-shoots-4",
    "description": "<img alt=\"Free Pixel Effects Pack #14 - Mini Magick Shoots 4\" src=\"https://img.itch.zone/aW1nLzQzNzUxNzguZ2lm/315x250%23c/oVSWCm.gif\"/>",
    "pubDate": "Wed, 07 Oct 2020 07:19:17 GMT",
    "createDate": "Wed, 07 Oct 2020 07:19:17 GMT",
    "updateDate": "Wed, 07 Oct 2020 08:49:11 GMT",
    "platforms": null
}