{
    "title": "Serpere",
    "id": 219226,
    "price": "$0.00",
    "cover_image": "https://img.itch.zone/aW1hZ2UvMjE5MjI2LzEwMzQ3MzIuZ2lm/315x250%23c/bkaCix.gif",
    "links": {
        "comments": "https://papercookies.itch.io/serpere/comments",
        "self": "https://papercookies.itch.io/serpere"
    },
    "tags": [
        "adventure",
        "did-i-mention-it-has-dodge-rolls",
        "dodge-rolls",
        "lowrez",
        "pixel-art",
        "short",
        "singleplayer"
    ],
    "authors": [
        {
            "name": "adam pype",
            "url": "https://papercookies.itch.io"
        }
    ]
}