{
    "title": "Stars of Canada",
    "id": 1044788,
    "cover_image": "https://img.itch.zone/aW1nLzU5NzAxNzIucG5n/315x250%23c/iMi0TZ.png",
    "links": {
        "comments": "https://milkbaggames.itch.io/stars-of-canada/comments",
        "self": "https://milkbaggames.itch.io/stars-of-canada"
    },
    "tags": [
        "chill",
        "music",
        "procedural",
        "puzzle",
        "tojam2021"
    ],
    "authors": [
        {
            "name": "Milkbag Games",
            "url": "https://milkbaggames.itch.io"
        }
    ]
}