{
    "guid": "https://xthekendrick.itch.io/exploisions-2d-pixelart-adventure-game",
    "title": "2D Pixel Art Explosion Pack 5 [$5.00]",
    "plainTitle": "2D Pixel Art Explosion Pack 5",
    "imageurl": "https://img.itch.zone/aW1nLzE4OTU3NjYzLnBuZw==/315x250%23c/5Gh%2Fkq.png",
    "price": "$5.00",
    "currency": "USD",
    "link": "https://xthekendrick.itch.io/exploisions-2d-pixelart-adventure-game",
    "description": "7 Amazing vfx pixelart explosions 32 x 32 and more\n<img alt=\"2D Pixel Art Explosion Pack 5\" src=\"https://img.itch.zone/aW1nLzE4OTU3NjYzLnBuZw==/315x250%23c/5Gh%2Fkq.png\"/>",
    "pubDate": "Mon, 01 Aug 2022 21:19:14 GMT",
    "createDate": "Mon, 01 Aug 2022 21:19:14 GMT",
    "updateDate": "Sun, 13 Apr 2025 18:08:32 GMT",
    "platforms": null
}