{
    "authors": [
        {
            "name": "Air Gong",
            "url": "https://air-gong.itch.io"
        }
    ],
    "id": 2272496,
    "price": "$0.00",
    "tags": [
        "creepy",
        "funny",
        "halloween",
        "horror",
        "kinetic-novel",
        "lgbt",
        "lgbtqia",
        "no-ai",
        "short",
        "transgender",
        "vampire",
        "visual-novel"
    ],
    "cover_image": "https://img.itch.zone/aW1nLzEzNDczMzA0LnBuZw==/315x250%23c/eGukwt.png",
    "links": {
        "devlog": "https://air-gong.itch.io/a-trick-and-a-treat/devlog",
        "self": "https://air-gong.itch.io/a-trick-and-a-treat",
        "comments": "https://air-gong.itch.io/a-trick-and-a-treat/comments"
    },
    "title": "A Trick and a Treat: Dead Letters (and one other)"
}