{
    "guid": "https://aiden-h.itch.io/timmys-math-adventure",
    "title": "Timmy's Math Adventure [Free] [Educational]",
    "plainTitle": "Timmy's Math Adventure",
    "imageurl": "https://img.itch.zone/aW1nLzIyMzc3ODQxLnBuZw==/315x250%23c/thZiDj.png",
    "price": "$0.00",
    "currency": "USD",
    "link": "https://aiden-h.itch.io/timmys-math-adventure",
    "description": "Fight monsters while practicing math!\n<img src=\"https://img.itch.zone/aW1nLzIyMzc3ODQxLnBuZw==/315x250%23c/thZiDj.png\" alt=\"Timmy&#039;s Math Adventure\"/>",
    "pubDate": "Mon, 28 Jul 2025 20:21:20 GMT",
    "createDate": "Mon, 28 Jul 2025 20:21:20 GMT",
    "updateDate": "Mon, 28 Jul 2025 20:42:43 GMT",
    "platforms": {
        "html": "yes"
    }
}