{
    "guid": "https://bdragon1727.itch.io/package-retro-60-pixel-fire-effects-fx",
    "title": "Package Retro +60 Pixel Fire Effects || FX Free [Free]",
    "plainTitle": "Package Retro +60 Pixel Fire Effects || FX Free",
    "imageurl": "https://img.itch.zone/aW1nLzEzMzQ4MTM0LmdpZg==/315x250%23c/I13KZS.gif",
    "price": "$0.00",
    "currency": "USD",
    "link": "https://bdragon1727.itch.io/package-retro-60-pixel-fire-effects-fx",
    "description": "<img alt=\"Package Retro +60 Pixel Fire Effects || FX Free\" src=\"https://img.itch.zone/aW1nLzEzMzQ4MTM0LmdpZg==/315x250%23c/I13KZS.gif\"/>",
    "pubDate": "Tue, 04 Jul 2023 09:39:00 GMT",
    "createDate": "Tue, 04 Jul 2023 09:39:00 GMT",
    "updateDate": "Thu, 07 Sep 2023 08:16:18 GMT",
    "platforms": null
}