{
    "guid": "https://henrysoftware.itch.io/free-pixel-effect",
    "title": "Free Pixel Effect! [Free]",
    "plainTitle": "Free Pixel Effect!",
    "imageurl": "https://img.itch.zone/aW1hZ2UvNTczNTkvMjU5MDg3LmdpZg==/315x250%23c/1Z%2F4LV.gif",
    "price": "$0.00",
    "currency": "USD",
    "link": "https://henrysoftware.itch.io/free-pixel-effect",
    "description": "Animated arrow tiles.\n<img alt=\"Free Pixel Effect!\" src=\"https://img.itch.zone/aW1hZ2UvNTczNTkvMjU5MDg3LmdpZg==/315x250%23c/1Z%2F4LV.gif\"/>",
    "pubDate": "Fri, 11 Mar 2016 20:34:18 GMT",
    "createDate": "Fri, 11 Mar 2016 20:34:18 GMT",
    "updateDate": "Sun, 03 Jun 2018 18:26:44 GMT",
    "platforms": {
        "html": "yes"
    }
}